{
  "name": "DATATBLS_GetItemTypeFieldE",
  "addr": 1876374992,
  "callconv": "stdcall",
  "ret": "i32",
  "args": [
    {
      "id": "idx",
      "kind": "i32"
    }
  ],
  "compare": [
    "ret"
  ],
  "vectors": [
    {
      "idx": 0
    },
    {
      "idx": 1
    },
    {
      "idx": 2
    },
    {
      "idx": 3
    },
    {
      "idx": 5
    },
    {
      "idx": 8
    },
    {
      "idx": 13
    },
    {
      "idx": 21
    },
    {
      "idx": 34
    },
    {
      "idx": 55
    },
    {
      "idx": 89
    },
    {
      "idx": 144
    },
    {
      "idx": -1
    },
    {
      "idx": 2147483647
    },
    {
      "idx": -2147483648
    },
    {
      "idx": 4
    },
    {
      "idx": 16
    },
    {
      "idx": 32
    },
    {
      "idx": 64
    },
    {
      "idx": 128
    },
    {
      "idx": 256
    },
    {
      "idx": 512
    },
    {
      "idx": 1024
    },
    {
      "idx": 2048
    },
    {
      "idx": 4096
    },
    {
      "idx": 8192
    },
    {
      "idx": 16384
    },
    {
      "idx": 32768
    },
    {
      "idx": 65536
    },
    {
      "idx": 131072
    },
    {
      "idx": 262144
    },
    {
      "idx": 524288
    },
    {
      "idx": 1048576
    },
    {
      "idx": 2097152
    },
    {
      "idx": 4194304
    },
    {
      "idx": 8388608
    },
    {
      "idx": 16777216
    },
    {
      "idx": 33554432
    },
    {
      "idx": 67108864
    },
    {
      "idx": 134217728
    },
    {
      "idx": 268435456
    },
    {
      "idx": 536870912
    },
    {
      "idx": 1073741824
    },
    {
      "idx": -2
    },
    {
      "idx": -128
    },
    {
      "idx": -32768
    },
    {
      "idx": 127
    },
    {
      "idx": 255
    },
    {
      "idx": 32767
    },
    {
      "idx": 32769
    },
    {
      "idx": 65535
    },
    {
      "idx": 65537
    }
  ]
}
